[
    {
        "appear_anime": "",
        "ui": 1,
        "size": 1,
        "effect": 1,
        "wave_id": 200111001,
        "clear": 1,
        "sim_select": 1,
        "death_anime": "",
        "card_id": 90901013,
        "aura": 1
    },
    {
        "appear_anime": "skill_ghost_appear_01",
        "ui": 1,
        "size": 1,
        "effect": 1,
        "wave_id": 200119003,
        "clear": 1,
        "sim_select": 1,
        "death_anime": "skill_ghost_death_01",
        "card_id": 93801010,
        "aura": 1
    },
    {
        "appear_anime": "skill_ghost_appear_01",
        "ui": 1,
        "size": 1,
        "effect": 1,
        "wave_id": 200122003,
        "clear": 1,
        "sim_select": 1,
        "death_anime": "skill_ghost_death_01",
        "card_id": 93801007,
        "aura": 1
    },
    {
        "appear_anime": "skill_alcor_appear_01",
        "ui": 1,
        "size": 0,
        "effect": 1,
        "wave_id": 200130003,
        "clear": 1,
        "sim_select": 1,
        "death_anime": "",
        "card_id": 93901001,
        "aura": 1
    },
    {
        "appear_anime": "skill_ghost_appear_01",
        "ui": 1,
        "size": 1,
        "effect": 1,
        "wave_id": 200201001,
        "clear": 1,
        "sim_select": 1,
        "death_anime": "skill_ghost_death_01",
        "card_id": 93801009,
        "aura": 1
    },
    {
        "appear_anime": "skill_ghost_appear_01",
        "ui": 1,
        "size": 1,
        "effect": 1,
        "wave_id": 200208003,
        "clear": 1,
        "sim_select": 1,
        "death_anime": "skill_ghost_death_01",
        "card_id": 93801009,
        "aura": 1
    },
    {
        "appear_anime": "skill_ghost_appear_01",
        "ui": 1,
        "size": 1,
        "effect": 1,
        "wave_id": 200211001,
        "clear": 1,
        "sim_select": 1,
        "death_anime": "skill_ghost_death_01",
        "card_id": 93801008,
        "aura": 1
    },
    {
        "appear_anime": "skill_ghost_appear_01",
        "ui": 1,
        "size": 1,
        "effect": 1,
        "wave_id": 200219003,
        "clear": 1,
        "sim_select": 1,
        "death_anime": "skill_ghost_death_01",
        "card_id": 93801009,
        "aura": 1
    },
    {
        "appear_anime": "skill_ghost_appear_01",
        "ui": 1,
        "size": 1,
        "effect": 1,
        "wave_id": 200222001,
        "clear": 1,
        "sim_select": 1,
        "death_anime": "skill_ghost_death_01",
        "card_id": 93801011,
        "aura": 1
    },
    {
        "appear_anime": "skill_alcor_appear_01",
        "ui": 1,
        "size": 0,
        "effect": 1,
        "wave_id": 200230001,
        "clear": 1,
        "sim_select": 1,
        "death_anime": "",
        "card_id": 93901002,
        "aura": 1
    },
    {
        "appear_anime": "skill_ghost_appear_01",
        "ui": 1,
        "size": 1,
        "effect": 1,
        "wave_id": 200304003,
        "clear": 1,
        "sim_select": 1,
        "death_anime": "skill_ghost_death_01",
        "card_id": 93801022,
        "aura": 1
    },
    {
        "appear_anime": "",
        "ui": 1,
        "size": 1,
        "effect": 1,
        "wave_id": 200309003,
        "clear": 1,
        "sim_select": 1,
        "death_anime": "",
        "card_id": 94601007,
        "aura": 1
    },
    {
        "appear_anime": "skill_ghost_appear_01",
        "ui": 1,
        "size": 1,
        "effect": 1,
        "wave_id": 200314003,
        "clear": 1,
        "sim_select": 1,
        "death_anime": "skill_ghost_death_01",
        "card_id": 93801023,
        "aura": 1
    },
    {
        "appear_anime": "",
        "ui": 1,
        "size": 1,
        "effect": 1,
        "wave_id": 200320003,
        "clear": 1,
        "sim_select": 1,
        "death_anime": "",
        "card_id": 94601008,
        "aura": 1
    },
    {
        "appear_anime": "skill_alcor_appear_01",
        "ui": 1,
        "size": 0,
        "effect": 1,
        "wave_id": 200326001,
        "clear": 1,
        "sim_select": 1,
        "death_anime": "",
        "card_id": 93901002,
        "aura": 1
    },
    {
        "appear_anime": "skill_ghost_appear_01",
        "ui": 1,
        "size": 1,
        "effect": 1,
        "wave_id": 200404001,
        "clear": 1,
        "sim_select": 1,
        "death_anime": "skill_ghost_death_01",
        "card_id": 93801028,
        "aura": 1
    },
    {
        "appear_anime": "skill_ghost_appear_01",
        "ui": 1,
        "size": 1,
        "effect": 1,
        "wave_id": 200414001,
        "clear": 1,
        "sim_select": 1,
        "death_anime": "skill_ghost_death_01",
        "card_id": 93801029,
        "aura": 1
    },
    {
        "appear_anime": "skill_ghost_appear_01",
        "ui": 1,
        "size": 1,
        "effect": 1,
        "wave_id": 200424001,
        "clear": 1,
        "sim_select": 1,
        "death_anime": "skill_ghost_death_01",
        "card_id": 93801030,
        "aura": 1
    },
    {
        "appear_anime": "skill_ghost_appear_01",
        "ui": 1,
        "size": 1,
        "effect": 1,
        "wave_id": 200430001,
        "clear": 1,
        "sim_select": 1,
        "death_anime": "skill_ghost_death_01",
        "card_id": 93801031,
        "aura": 1
    },
    {
        "appear_anime": "",
        "ui": 1,
        "size": 1,
        "effect": 1,
        "wave_id": 200501001,
        "clear": 1,
        "sim_select": 1,
        "death_anime": "",
        "card_id": 94201001,
        "aura": 1
    },
    {
        "appear_anime": "",
        "ui": 1,
        "size": 1,
        "effect": 1,
        "wave_id": 200511001,
        "clear": 1,
        "sim_select": 1,
        "death_anime": "",
        "card_id": 94201002,
        "aura": 1
    },
    {
        "appear_anime": "",
        "ui": 1,
        "size": 0,
        "effect": 1,
        "wave_id": 200530001,
        "clear": 1,
        "sim_select": 1,
        "death_anime": "",
        "card_id": 99801001,
        "aura": 1
    }
]